{
  "name": "本周话题：数字人民币要取代谁",
  "slug": "ben-zhou-hua-ti-shu-zi-ren-min-bi-yao-qu-dai-shui",
  "count": 1,
  "items": [
    {
      "issueId": 125,
      "issueTitle": "科技爱好者周刊（第 125 期）：数字人民币要取代谁",
      "content": "\n数字人民币，已经传了很久了，但它到底是什么东西，媒体却不提。\n\n本周，人民银行的副行长写了[一篇文章](https://www.financialnews.com.cn/ll/gdsj/202009/t20200914_200849.html)，第一段就回答了这个问题。\n\n> “数字人民币主要定位于流通中现金。……国家有必要利用新技术对现金进行数字化，为数字经济发展提供通用性的基础货币。”\n\n![](https://cdn.beekka.com/blogimg/asset/202009/bg2020091414.jpg)\n\n现在清楚了，数字人民币根本不是加密货币，而是人民币现金的数字形式，主要用于网上支付。\n\n但是，网上支付早不是问题了，支付宝和微信支付用得好好的，为什么央行还要推行数字人民币呢？上面那篇文章，同样解释了数字人民币的运作模式。\n\n>  **“中央银行在数字人民币体系中居于中心地位，负责向指定商业银行批发数字人民币并进行全生命周期管理，商业银行等机构负责面向社会公众提供数字人民币兑换流通服务。”**\n\n看到了吗，中央银行主管数字人民币，只有指定的商业银行才能对公众提供服务。也就是说，以后网上支付的时候，你不会只用微信支付和支付宝，还可以用商业银行的客户端。这就是说， **数字人民币就是商业银行的网上支付服务。**\n\n前一段时间，建行的数字人民币客户端泄漏。顶部的四个主要功能按钮是付款、收款、扫一扫和转款，正好验证了央行的说法。\n\n![](https://cdn.beekka.com/blogimg/asset/202009/bg2020091413.jpg)\n\n我想，这就是中央银行想要推广数字人民币的主要原因。现在的局面是，两家互联网巨头，掌握了全国的数字支付，它们还都是私人公司。国有商业银行和银联的云闪付，根本拿不到市场份额。中央银行应该是比较担心这个，不愿数字支付被腾讯和阿里垄断，希望商业银行能挤进去。\n\n这对消费者是有利的。两大巨头现在各占山头，阿里系不支持微信支付，腾讯系不支持支付宝。数字人民币出来以后，所有平台都必须支持（它是法定货币）。我猜想，将来应该只有一个统一的二维码，不管是用微信、支付宝还是商业银行的 App 扫描，都能支付。不像现在，商家都要贴两个二维码，蓝的一个、绿的一个。\n\n![](https://cdn.beekka.com/blogimg/asset/202009/bg2020091703.jpg)\n\n但是，数字支付业务其实是无利可图的。它不像信用卡支付，提供方不仅赚不到手续费，还要往里面贴钱。维护硬件和开发软件都需要巨大的投入，而且对可靠性的要求特别高，服务不能中断，更不能出错。微信和支付宝其实都把扫码支付当作流量入口，而不是利润来源。\n\n我很好奇，数字人民币的服务器，将来由谁维护？是不是中央银行以后也会有一个专门的 DevOps 部门？但是，这种赚不到钱、技术难度大、工程师薪水又极高的业务，国有单位能搞好吗？\n"
    }
  ]
}